pyzig.py
pyzig-0.0.2a0.dist-info/LICENSE
pyzig-0.0.2a0.dist-info/METADATA
pyzig-0.0.2a0.dist-info/WHEEL
pyzig-0.0.2a0.dist-info/top_level.txt
pyzig-0.0.2a0.dist-info/RECORD
