Metadata-Version: 2.1
Name: pyzig
Version: 0.0.2a0
Summary: Build Python extensions with the Zig language
Author-email: february cozzocrea <february.cozzocrea@gmail.com>
License: MIT License
Project-URL: Homepage, https://github.com/f-cozzocrea/pyzig
Project-URL: Bug Tracker, https://github.com/f-cozzocrea/pyzig/issues
Classifier: License :: OSI Approved :: MIT License
Classifier: Programming Language :: Python :: 3
Classifier: Programming Language :: Python :: 3 :: Only
Classifier: Programming Language :: Python :: 3.8
Classifier: Programming Language :: Python :: 3.9
Classifier: Programming Language :: Python :: 3.10
Classifier: Programming Language :: Python :: 3.11
Classifier: Programming Language :: Python :: Implementation :: CPython
Requires-Python: >=3.7
License-File: LICENSE
